{
  "name": "prototypeElkIslandVFE",
  "defaultPhotosphereID": "South",
  "map": {
    "id": "navmap",
    "src": {
      "tag": "Runtime",
      "path": "/VFEdata/map.jpg",
      "id": "map.jpg"
    },
    "rotation": 0,
    "defaultZoom": 20,
    "defaultCenter": {
      "x": 592.5,
      "y": 511.5
    },
    "width": 1185,
    "height": 1023,
    "size": 300
  },
  "photospheres": {
    "South": {
      "id": "South",
      "src": {
        "tag": "Runtime",
        "path": "/VFEdata/ERI_SouthScene_6-IMG_20231006_081813_00_122.jpg",
        "id": "SouthScene.jpg"
      },
      "center": {
        "x": 450,
        "y": 800
      },
      "timeline": {
        "2020-10-10": "CHILD_South_1",
        "2000-12-10": "CHILD_South_2"
      },
      "hotspots": {
        "OutcropWideView": {
          "id": "OutcropWideView",
          "elevation": 5,
          "direction": -5,
          "icon": {
            "tag": "Runtime",
            "path": "/pin-blue.png",
            "id": "blue-pin.png"
          },
          "tooltip": "OutcropWideView",
          "data": {
            "tag": "Image",
            "width": 3024,
            "height": 4032,
            "src": {
              "tag": "Runtime",
              "path": "/VFEdata/outcropWideView.png",
              "id": "outcrop.jpg"
            },
            "hotspots": {}
          },
          "level": 1
        },
        "Flowers": {
          "id": "Flowers",
          "elevation": -3,
          "direction": 18,
          "icon": {
            "tag": "Runtime",
            "path": "/pin-blue.png",
            "id": "blue-pin.png"
          },
          "tooltip": "Flowers",
          "data": {
            "tag": "Image",
            "width": 3024,
            "height": 4032,
            "src": {
              "tag": "Runtime",
              "path": "/VFEdata/flowers.png",
              "id": "flowers.png"
            },
            "hotspots": {}
          },
          "level": 1
        },
        "URLDemo": {
          "id": "URLDemo",
          "elevation": -10,
          "direction": 0,
          "icon": {
            "tag": "Runtime",
            "path": "/pin-blue.png",
            "id": "blue-pin.png"
          },
          "tooltip": "URLDemo",
          "data": {
            "tag": "URL",
            "url": "https://virtual-field-environments.vercel.app/"
          },
          "level": 1
        },
        "AudioDemo": {
          "id": "AudioDemo",
          "elevation": -10,
          "direction": 10,
          "icon": {
            "tag": "Runtime",
            "path": "/pin-blue.png",
            "id": "blue-pin.png"
          },
          "tooltip": "Audio Demo - FrogChorus.mp3",
          "data": {
            "tag": "Audio",
            "src": {
              "tag": "Runtime",
              "path": "/VFEdata/FrogChorus.LS100206.mp3",
              "id": "frogs.mp3"
            }
          },
          "level": 1
        },
        "DocumentDemo": {
          "id": "DocumentDemo",
          "elevation": -10,
          "direction": 20,
          "icon": {
            "tag": "Runtime",
            "path": "/pin-blue.png",
            "id": "blue-pin.png"
          },
          "tooltip": "Document Demo - VFE Guidelines",
          "data": {
            "tag": "Doc",
            "src": {
              "tag": "Runtime",
              "path": "/VFEdata/General guide - Virtual Field Environments for Student-based Inquiry.pdf",
              "id": "inquiry.pdf"
            }
          },
          "level": 1
        },
        "ShorelineSOUTH": {
          "id": "ShorelineSOUTH",
          "elevation": -32,
          "direction": 172,
          "icon": {
            "tag": "Runtime",
            "path": "/pin-red.png",
            "id": "red-pin.png"
          },
          "tooltip": "ShorelineSOUTH.mp4",
          "data": {
            "tag": "Video",
            "src": {
              "tag": "Runtime",
              "path": "/VFEdata/shorelineSOUTH.mp4",
              "id": "shorelineSouth.mp4"
            }
          },
          "level": 1
        },
        "Paddlers": {
          "id": "Paddlers",
          "elevation": -10,
          "direction": -175,
          "icon": {
            "tag": "Runtime",
            "path": "/pin-red.png",
            "id": "red-pin.png"
          },
          "tooltip": "Paddlers.mp4",
          "data": {
            "tag": "Video",
            "src": {
              "tag": "Runtime",
              "path": "/VFEdata/paddlers.mp4",
              "id": "paddlers.mp4"
            }
          },
          "level": 1
        },
        "SmallPool": {
          "id": "SmallPool",
          "elevation": -13,
          "direction": 100,
          "icon": {
            "tag": "Runtime",
            "path": "/pin-blue.png",
            "id": "blue-pin.png"
          },
          "tooltip": "SmallPool",
          "data": {
            "tag": "Image",
            "width": 1344,
            "height": 1792,
            "src": {
              "tag": "Runtime",
              "path": "/VFEdata/small_pool.jpg",
              "id": "small-pool.jpg"
            },
            "hotspots": {}
          },
          "level": 1
        },
        "LogNearShoreline": {
          "id": "LogNearShoreline",
          "elevation": -25,
          "direction": -40,
          "icon": {
            "tag": "Runtime",
            "path": "/pin-blue.png",
            "id": "blue-pin.png"
          },
          "tooltip": "LogNearShoreline",
          "data": {
            "tag": "Image",
            "width": 3024,
            "height": 4032,
            "src": {
              "tag": "Runtime",
              "path": "/VFEdata/logNEARshoreline.png",
              "id": "logShoreline.png"
            },
            "hotspots": {}
          },
          "level": 1
        },
        "CoolLog": {
          "id": "CoolLog",
          "elevation": -17,
          "direction": -33,
          "icon": {
            "tag": "Runtime",
            "path": "/pin-blue.png",
            "id": "blue-pin.png"
          },
          "tooltip": "CoolLog",
          "data": {
            "tag": "Image",
            "width": 1792,
            "height": 1344,
            "src": {
              "tag": "Runtime",
              "path": "/VFEdata/cool_log.jpeg",
              "id": "cool-log.jpeg"
            },
            "hotspots": {}
          },
          "level": 1
        },
        "OutcropTextures": {
          "id": "OutcropTextures",
          "elevation": 6,
          "direction": 5,
          "icon": {
            "tag": "Runtime",
            "path": "/pin-red.png",
            "id": "red-pin.png"
          },
          "tooltip": "OutcropTextures",
          "data": {
            "tag": "Video",
            "src": {
              "tag": "Runtime",
              "path": "/VFEdata/outcrop_textures.mp4",
              "id": "outcrop-textures.mp4"
            }
          },
          "level": 1
        },
        "HugeLogs": {
          "id": "HugeLogs",
          "elevation": -12,
          "direction": -37,
          "icon": {
            "tag": "Runtime",
            "path": "/pin-blue.png",
            "id": "blue-pin.png"
          },
          "tooltip": "How did these huge logs get here?",
          "data": {
            "tag": "Message",
            "content": "How did these huge logs get here?"
          },
          "level": 1
        },
        "Mushroom": {
          "id": "Mushroom",
          "elevation": 2,
          "direction": -19,
          "icon": {
            "tag": "Runtime",
            "path": "/pin-blue.png",
            "id": "blue-pin.png"
          },
          "tooltip": "Mushroom",
          "data": {
            "tag": "Image",
            "width": 3024,
            "height": 4032,
            "src": {
              "tag": "Runtime",
              "path": "/VFEdata/mushroom.png",
              "id": "mushroom.png"
            },
            "hotspots": {}
          },
          "level": 1
        },
        "Contact": {
          "id": "Contact",
          "elevation": 2,
          "direction": -46,
          "icon": {
            "tag": "Runtime",
            "path": "/pin-blue.png",
            "id": "blue-pin.png"
          },
          "tooltip": "Contact",
          "data": {
            "tag": "Image",
            "width": 2549,
            "height": 1694,
            "src": {
              "tag": "Runtime",
              "path": "/VFEdata/Contact.png",
              "id": "contact.png"
            },
            "hotspots": {
              "HandSample": {
                "x": 12.5,
                "y": 32.5,
                "id": "HandSample",
                "tooltip": "HandSample",
                "color": "#FF0000",
                "data": {
                  "tag": "Image",
                  "width": 1342,
                  "height": 1064,
                  "src": {
                    "tag": "Runtime",
                    "path": "/VFEdata/hand_sample.png",
                    "id": "hand-sample.png"
                  },
                  "hotspots": {
                    "CloserLook": {
                      "x": 63,
                      "y": 56,
                      "id": "CloserLook",
                      "tooltip": "CloserLook",
                      "color": "#00FF00",
                      "data": {
                        "tag": "Image",
                        "width": 4240,
                        "height": 2832,
                        "src": {
                          "tag": "Runtime",
                          "path": "/VFEdata/a-closer-look.jpg",
                          "id": "a-closer-look.jpg"
                        },
                        "hotspots": {
                          "SouthSEMComparison": {
                            "x": 52,
                            "y": 35,
                            "id": "SouthSEMComparison",
                            "tooltip": "SouthSEMComparison",
                            "color": "#00FFFF",
                            "data": {
                              "tag": "Image",
                              "width": 720,
                              "height": 312,
                              "src": {
                                "tag": "Runtime",
                                "path": "/VFEdata/southSEMcomp.png",
                                "id": "southSEMcomp.png"
                              },
                              "hotspots": {}
                            }
                          }
                        }
                      }
                    }
                  }
                }
              }
            }
          },
          "level": 1
        },
        "SouthWaterfront": {
          "id": "SouthWaterfront",
          "elevation": -1,
          "direction": -25,
          "icon": {
            "tag": "Runtime",
            "path": "/pin-blue.png",
            "id": "blue-pin.png"
          },
          "tooltip": "SouthWaterfront",
          "data": {
            "tag": "Image",
            "width": 3024,
            "height": 4032,
            "src": {
              "tag": "Runtime",
              "path": "/VFEdata/SouthwaterFront.png",
              "id": "south-waterfront.png"
            },
            "hotspots": {}
          },
          "level": 1
        },
        "Go West": {
          "id": "Go West",
          "elevation": 0,
          "direction": -35,
          "icon": {
            "tag": "Runtime",
            "path": "/pin-blue.png",
            "id": "blue-pin.png"
          },
          "tooltip": "Go West",
          "data": {
            "tag": "PhotosphereLink",
            "photosphereID": "West"
          },
          "level": 0
        },
        "Go to Entrance": {
          "id": "Go to Entrance",
          "elevation": -7,
          "direction": 125,
          "icon": {
            "tag": "Runtime",
            "path": "/pin-blue.png",
            "id": "blue-pin.png"
          },
          "tooltip": "Go to Entrance",
          "data": {
            "tag": "PhotosphereLink",
            "photosphereID": "Entrance"
          },
          "level": 0
        }
      },
      "backgroundAudio": {
        "tag": "Runtime",
        "path": "/VFEdata/Scene12_UnevenStandTop_LS100146.mp3",
        "id": "scene12.mp3"
      }
    },
    "Entrance": {
      "id": "Entrance",
      "src": {
        "tag": "Runtime",
        "path": "/VFEdata/ERI_Entrance-Scene0-IMG_20231006_080232_00_120.jpg",
        "id": "entrance.jpg"
      },
      "center": {
        "x": 650,
        "y": 930
      },
      "hotspots": {
        "Go East": {
          "id": "Go East",
          "elevation": -2,
          "direction": -4,
          "icon": {
            "tag": "Runtime",
            "path": "/pin-blue.png",
            "id": "blue-pin.png"
          },
          "tooltip": "Go East",
          "data": {
            "tag": "PhotosphereLink",
            "photosphereID": "East"
          },
          "level": 0
        },
        "Go South": {
          "id": "Go South",
          "elevation": -4,
          "direction": -78,
          "icon": {
            "tag": "Runtime",
            "path": "/pin-blue.png",
            "id": "blue-pin.png"
          },
          "tooltip": "Go South",
          "data": {
            "tag": "PhotosphereLink",
            "photosphereID": "South"
          },
          "level": 0
        }
      },
      "timeline": {}
    },
    "West": {
      "id": "West",
      "src": {
        "tag": "Runtime",
        "path": "/VFEdata/ERI_West-Scene7-IMG_20231006_084114_00_123.jpg",
        "id": "west.jpg"
      },
      "center": {
        "x": 95,
        "y": 530
      },
      "hotspots": {
        "Go North": {
          "id": "Go North",
          "elevation": 0,
          "direction": 10,
          "icon": {
            "tag": "Runtime",
            "path": "/pin-blue.png",
            "id": "blue-pin.png"
          },
          "tooltip": "Go North",
          "data": {
            "tag": "PhotosphereLink",
            "photosphereID": "North"
          },
          "level": 0
        },
        "Go South": {
          "id": "Go South",
          "elevation": -3,
          "direction": 115,
          "icon": {
            "tag": "Runtime",
            "path": "/pin-blue.png",
            "id": "blue-pin.png"
          },
          "tooltip": "Go South",
          "data": {
            "tag": "PhotosphereLink",
            "photosphereID": "South"
          },
          "level": 0
        }
      },
      "timeline": {}
    },
    "North": {
      "id": "North",
      "src": {
        "tag": "Runtime",
        "path": "/VFEdata/ERI_North-Scene8-IMG_20231006_091050_00_124.jpg",
        "id": "north.jpg"
      },
      "center": {
        "x": 390,
        "y": 50
      },
      "hotspots": {
        "Go West": {
          "id": "Go West",
          "elevation": 0,
          "direction": -130,
          "icon": {
            "tag": "Runtime",
            "path": "/pin-blue.png",
            "id": "blue-pin.png"
          },
          "tooltip": "Go West",
          "data": {
            "tag": "PhotosphereLink",
            "photosphereID": "West"
          },
          "level": 0
        },
        "Go East": {
          "id": "Go East",
          "elevation": 0,
          "direction": 92,
          "icon": {
            "tag": "Runtime",
            "path": "/pin-blue.png",
            "id": "blue-pin.png"
          },
          "tooltip": "Go East",
          "data": {
            "tag": "PhotosphereLink",
            "photosphereID": "East"
          },
          "level": 0
        }
      },
      "timeline": {}
    },
    "East": {
      "id": "East",
      "src": {
        "tag": "Runtime",
        "path": "/VFEdata/ERI_East-Scene9-IMG_20231006_092207_00_125.jpg",
        "id": "east.jpg"
      },
      "center": {
        "x": 550,
        "y": 450
      },
      "hotspots": {
        "Go North": {
          "id": "Go North",
          "elevation": 3,
          "direction": 2,
          "icon": {
            "tag": "Runtime",
            "path": "/pin-blue.png",
            "id": "blue-pin.png"
          },
          "tooltip": "Go North",
          "data": {
            "tag": "PhotosphereLink",
            "photosphereID": "North"
          },
          "level": 0
        },
        "Go to Entrance": {
          "id": "Go to Entrance",
          "elevation": -2,
          "direction": -167,
          "icon": {
            "tag": "Runtime",
            "path": "/pin-blue.png",
            "id": "blue-pin.png"
          },
          "tooltip": "Go to Entrance",
          "data": {
            "tag": "PhotosphereLink",
            "photosphereID": "Entrance"
          },
          "level": 0
        }
      },
      "timeline": {}
    },
    "CHILD_South_1": {
      "id": "CHILD_South_1",
      "src": {
        "tag": "Stored",
        "id": "d2a16d62-b492-4ea9-ab14-545b8b434df3",
        "path": "d2a16d62-b492-4ea9-ab14-545b8b434df3"
      },
      "hotspots": {
        "e2513edd-0e11-4d4a-819d-c8e9627260be": {
          "id": "e2513edd-0e11-4d4a-819d-c8e9627260be",
          "tooltip": "WHALE!",
          "elevation": 0.2954789294646916,
          "direction": 230.20045523538158,
          "level": 0,
          "icon": {
            "tag": "Runtime",
            "id": "0da36818-ef17-4f31-a8f4-facedb027e87",
            "path": "/pin-blue.png"
          },
          "data": {
            "tag": "Message",
            "content": "There used to be whales here"
          }
        },
        "3bd94eef-01b5-4981-a941-4a5d35004314": {
          "id": "3bd94eef-01b5-4981-a941-4a5d35004314",
          "tooltip": "Trees",
          "elevation": 0.63427033960122,
          "direction": 130.84256823803437,
          "level": 0,
          "icon": {
            "tag": "Runtime",
            "id": "f457a67f-da19-4206-94af-e6ba4df5193c",
            "path": "/pin-blue.png"
          },
          "data": {
            "tag": "Message",
            "content": "Trees were thriving"
          }
        },
        "519d8c14-2ba2-4da2-b8a3-9cf860a2b61c": {
          "id": "519d8c14-2ba2-4da2-b8a3-9cf860a2b61c",
          "tooltip": "Whale recording",
          "elevation": -11.371125486525557,
          "direction": 228.25943434974107,
          "level": 0,
          "icon": {
            "tag": "Runtime",
            "id": "924f17f9-622c-4a0a-ae33-7e32db79e3dc",
            "path": "/pin-blue.png"
          },
          "data": {
            "tag": "Audio",
            "src": {
              "tag": "Stored",
              "id": "86e7f64b-9d40-4951-9e99-6b04aa6e5b08",
              "path": "86e7f64b-9d40-4951-9e99-6b04aa6e5b08"
            }
          }
        },
	"Go West": {
          "id": "Go West",
          "elevation": 0,
          "direction": -35,
          "icon": {
            "tag": "Runtime",
            "path": "/pin-blue.png",
            "id": "blue-pin.png"
          },
          "tooltip": "Go West",
          "data": {
            "tag": "PhotosphereLink",
            "photosphereID": "West"
          },
          "level": 0
        },
        "Go to Entrance": {
          "id": "Go to Entrance",
          "elevation": -7,
          "direction": 125,
          "icon": {
            "tag": "Runtime",
            "path": "/pin-blue.png",
            "id": "blue-pin.png"
          },
          "tooltip": "Go to Entrance",
          "data": {
            "tag": "PhotosphereLink",
            "photosphereID": "Entrance"
          },
          "level": 0
        }
      },
      "timeline": {},
      "parentPS": "South"
    },
    "CHILD_South_2": {
      "id": "CHILD_South_2",
      "src": {
        "tag": "Stored",
        "id": "cf0fab31-cf8b-4689-a7e4-c600c5c07dbc",
        "path": "cf0fab31-cf8b-4689-a7e4-c600c5c07dbc"
      },
      "hotspots": {
        "c5651e47-e7f3-463c-afab-9a9a0feea438": {
          "id": "c5651e47-e7f3-463c-afab-9a9a0feea438",
          "tooltip": "Bad Weather?",
          "elevation": 7.712088030949307,
          "direction": 356.2424384813748,
          "level": 0,
          "icon": {
            "tag": "Runtime",
            "id": "0baca2a9-341e-4dd2-a41b-4ec47206811b",
            "path": "/pin-blue.png"
          },
          "data": {
            "tag": "Message",
            "content": "There appears to be bad climate during this time"
          }
        },
        "ca4c7b2d-27f1-4e4a-b317-2f8ae1d98daa": {
          "id": "ca4c7b2d-27f1-4e4a-b317-2f8ae1d98daa",
          "tooltip": "Less trees then now",
          "elevation": 5.544461505472647,
          "direction": 43.1805411063664,
          "level": 0,
          "icon": {
            "tag": "Runtime",
            "id": "c1f7b2b6-87c9-46e2-8387-c74cb2309d9b",
            "path": "/pin-red.png"
          },
          "data": {
            "tag": "Image",
            "src": {
              "tag": "Stored",
              "id": "791e42af-21cc-4d22-8230-093e443265e2",
              "path": "791e42af-21cc-4d22-8230-093e443265e2"
            },
            "width": 673,
            "height": 452,
            "hotspots": {}
          }
        },
	"Go West": {
          "id": "Go West",
          "elevation": 0,
          "direction": -35,
          "icon": {
            "tag": "Runtime",
            "path": "/pin-blue.png",
            "id": "blue-pin.png"
          },
          "tooltip": "Go West",
          "data": {
            "tag": "PhotosphereLink",
            "photosphereID": "West"
          },
          "level": 0
        },
        "Go to Entrance": {
          "id": "Go to Entrance",
          "elevation": -7,
          "direction": 125,
          "icon": {
            "tag": "Runtime",
            "path": "/pin-blue.png",
            "id": "blue-pin.png"
          },
          "tooltip": "Go to Entrance",
          "data": {
            "tag": "PhotosphereLink",
            "photosphereID": "Entrance"
          },
          "level": 0
        }
      },
      "timeline": {},
      "parentPS": "South"
    }
  }
}
